wechatter/__init__.py
wechatter/version.py
wechatter-1.0.0.dist-info/LICENSE
wechatter-1.0.0.dist-info/METADATA
wechatter-1.0.0.dist-info/WHEEL
wechatter-1.0.0.dist-info/entry_points.txt
wechatter-1.0.0.dist-info/top_level.txt
wechatter-1.0.0.dist-info/RECORD
