Metadata-Version: 2.1
Name: wechatter
Version: 1.0.0
Summary: Open source deep learning framework to automate text- and voice-based conversations
Home-page: https://we-chatter.com
Author: wechatter community
Author-email: charlesxu86@163.com
Maintainer: wechatter
Maintainer-email: charlesxu86@163.com
License: UNKNOWN
Platform: UNKNOWN
Requires-Python: >=3.6
Requires-Dist: tensorflow (>=2.1)
